{
  "type": "Feature",
  "stac_version": "1.1.0",
  "stac_extensions": [
    "https://stac-extensions.github.io/projection/v2.0.0/schema.json",
    "https://stac-extensions.github.io/raster/v1.1.0/schema.json"
  ],
  "id": "USGS_1M_16_x77y372_GA_Statewide_2018_B18_DRRA",
  "geometry": {
    "type": "Polygon",
    "coordinates": [
      [
        [
          -84.09389946632425,
          33.49543662205045
        ],
        [
          -83.98626221492485,
          33.49286326788132
        ],
        [
          -83.98312822833876,
          33.583042038498135
        ],
        [
          -84.09087701977589,
          33.5856241528701
        ],
        [
          -84.09389946632425,
          33.49543662205045
        ]
      ]
    ]
  },
  "bbox": [
    -84.09389946632425,
    33.49286326788132,
    -83.98312822833876,
    33.5856241528701
  ],
  "properties": {
    "start_datetime": "2018-11-27T00:00:00Z",
    "end_datetime": "2019-04-03T00:00:00Z",
    "proj:geometry": {
      "type": "Polygon",
      "coordinates": [
        [
          [
            769993.9996988897,
            3709994.0002813223
          ],
          [
            780005.9996988897,
            3709994.0002813223
          ],
          [
            780005.9996988897,
            3720006.0002813223
          ],
          [
            769993.9996988897,
            3720006.0002813223
          ],
          [
            769993.9996988897,
            3709994.0002813223
          ]
        ]
      ]
    },
    "proj:bbox": [
      769993.9996988897,
      3709994.0002813223,
      780005.9996988897,
      3720006.0002813223
    ],
    "proj:shape": [
      10012,
      10012
    ],
    "proj:transform": [
      1.0,
      0.0,
      769993.9996988897,
      0.0,
      -1.0,
      3720006.0002813223,
      0.0,
      0.0,
      1.0
    ],
    "proj:projjson": {
      "$schema": "https://proj.org/schemas/v0.7/projjson.schema.json",
      "type": "ProjectedCRS",
      "name": "NAD83 / UTM zone 16N",
      "base_crs": {
        "name": "NAD83",
        "datum": {
          "type": "GeodeticReferenceFrame",
          "name": "North American Datum 1983",
          "ellipsoid": {
            "name": "GRS 1980",
            "semi_major_axis": 6378137,
            "inverse_flattening": 298.257222101
          }
        },
        "coordinate_system": {
          "subtype": "ellipsoidal",
          "axis": [
            {
              "name": "Geodetic latitude",
              "abbreviation": "Lat",
              "direction": "north",
              "unit": "degree"
            },
            {
              "name": "Geodetic longitude",
              "abbreviation": "Lon",
              "direction": "east",
              "unit": "degree"
            }
          ]
        },
        "id": {
          "authority": "EPSG",
          "code": 4269
        }
      },
      "conversion": {
        "name": "UTM zone 16N",
        "method": {
          "name": "Transverse Mercator",
          "id": {
            "authority": "EPSG",
            "code": 9807
          }
        },
        "parameters": [
          {
            "name": "Latitude of natural origin",
            "value": 0,
            "unit": "degree",
            "id": {
              "authority": "EPSG",
              "code": 8801
            }
          },
          {
            "name": "Longitude of natural origin",
            "value": -87,
            "unit": "degree",
            "id": {
              "authority": "EPSG",
              "code": 8802
            }
          },
          {
            "name": "Scale factor at natural origin",
            "value": 0.9996,
            "unit": "unity",
            "id": {
              "authority": "EPSG",
              "code": 8805
            }
          },
          {
            "name": "False easting",
            "value": 500000,
            "unit": "metre",
            "id": {
              "authority": "EPSG",
              "code": 8806
            }
          },
          {
            "name": "False northing",
            "value": 0,
            "unit": "metre",
            "id": {
              "authority": "EPSG",
              "code": 8807
            }
          }
        ]
      },
      "coordinate_system": {
        "subtype": "Cartesian",
        "axis": [
          {
            "name": "Easting",
            "abbreviation": "",
            "direction": "east",
            "unit": "metre"
          },
          {
            "name": "Northing",
            "abbreviation": "",
            "direction": "north",
            "unit": "metre"
          }
        ]
      },
      "id": {
        "authority": "EPSG",
        "code": 26916
      }
    },
    "datetime": null,
    "proj:code": "EPSG:26916"
  },
  "links": [
    {
      "rel": "root",
      "href": "./collection.json",
      "type": "application/json"
    },
    {
      "rel": "collection",
      "href": "./collection.json",
      "type": "application/json"
    },
    {
      "rel": "parent",
      "href": "./collection.json",
      "type": "application/json"
    }
  ],
  "assets": {
    "elevation": {
      "href": "https://prd-tnm.s3.amazonaws.com/StagedProducts/Elevation/1m/Projects/GA_Statewide_2018_B18_DRRA/TIFF/USGS_1M_16_x77y372_GA_Statewide_2018_B18_DRRA.tif",
      "type": "image/tiff; application=geotiff",
      "raster:bands": [
        {
          "data_type": "float32",
          "scale": 1.0,
          "offset": 0.0,
          "sampling": "area",
          "nodata": -999999.0,
          "unit": "metre",
          "statistics": {
            "mean": 216.15959229956164,
            "minimum": 176.68765258789062,
            "maximum": 252.83070373535156,
            "stddev": 15.804658037871425,
            "valid_percent": 52.06022262573242
          },
          "histogram": {
            "count": 11,
            "min": 176.68765258789062,
            "max": 252.83070373535156,
            "buckets": [
              8094,
              38397,
              50823,
              65751,
              83930,
              84072,
              87457,
              85150,
              39408,
              2809
            ]
          }
        }
      ],
      "roles": [
        "data"
      ]
    }
  },
  "collection": "GA_Statewide_2018_B18_DRRA"
}