{
  "type": "Feature",
  "stac_version": "1.1.0",
  "stac_extensions": [
    "https://stac-extensions.github.io/projection/v2.0.0/schema.json",
    "https://stac-extensions.github.io/raster/v1.1.0/schema.json"
  ],
  "id": "USGS_1M_13_x58y524_ND_SouthWest_2021_D21",
  "geometry": {
    "type": "Polygon",
    "coordinates": [
      [
        [
          -103.94348079654513,
          47.21856271181989
        ],
        [
          -103.81127509587044,
          47.21726722657195
        ],
        [
          -103.80925688902275,
          47.30733925639264
        ],
        [
          -103.94168693897349,
          47.30863880670267
        ],
        [
          -103.94348079654513,
          47.21856271181989
        ]
      ]
    ]
  },
  "bbox": [
    -103.94348079654513,
    47.21726722657195,
    -103.80925688902275,
    47.30863880670267
  ],
  "properties": {
    "start_datetime": "2021-10-29T00:00:00Z",
    "end_datetime": "2021-11-08T00:00:00Z",
    "proj:geometry": {
      "type": "Polygon",
      "coordinates": [
        [
          [
            579993.9999868791,
            5229993.999998578
          ],
          [
            590005.9999868791,
            5229993.999998578
          ],
          [
            590005.9999868791,
            5240005.999998578
          ],
          [
            579993.9999868791,
            5240005.999998578
          ],
          [
            579993.9999868791,
            5229993.999998578
          ]
        ]
      ]
    },
    "proj:bbox": [
      579993.9999868791,
      5229993.999998578,
      590005.9999868791,
      5240005.999998578
    ],
    "proj:shape": [
      10012,
      10012
    ],
    "proj:transform": [
      1.0,
      0.0,
      579993.9999868791,
      0.0,
      -1.0,
      5240005.999998578,
      0.0,
      0.0,
      1.0
    ],
    "proj:projjson": {
      "$schema": "https://proj.org/schemas/v0.7/projjson.schema.json",
      "type": "ProjectedCRS",
      "name": "NAD83 / UTM zone 13N",
      "base_crs": {
        "name": "NAD83",
        "datum": {
          "type": "GeodeticReferenceFrame",
          "name": "North American Datum 1983",
          "ellipsoid": {
            "name": "GRS 1980",
            "semi_major_axis": 6378137,
            "inverse_flattening": 298.257222101
          }
        },
        "coordinate_system": {
          "subtype": "ellipsoidal",
          "axis": [
            {
              "name": "Geodetic latitude",
              "abbreviation": "Lat",
              "direction": "north",
              "unit": "degree"
            },
            {
              "name": "Geodetic longitude",
              "abbreviation": "Lon",
              "direction": "east",
              "unit": "degree"
            }
          ]
        },
        "id": {
          "authority": "EPSG",
          "code": 4269
        }
      },
      "conversion": {
        "name": "UTM zone 13N",
        "method": {
          "name": "Transverse Mercator",
          "id": {
            "authority": "EPSG",
            "code": 9807
          }
        },
        "parameters": [
          {
            "name": "Latitude of natural origin",
            "value": 0,
            "unit": "degree",
            "id": {
              "authority": "EPSG",
              "code": 8801
            }
          },
          {
            "name": "Longitude of natural origin",
            "value": -105,
            "unit": "degree",
            "id": {
              "authority": "EPSG",
              "code": 8802
            }
          },
          {
            "name": "Scale factor at natural origin",
            "value": 0.9996,
            "unit": "unity",
            "id": {
              "authority": "EPSG",
              "code": 8805
            }
          },
          {
            "name": "False easting",
            "value": 500000,
            "unit": "metre",
            "id": {
              "authority": "EPSG",
              "code": 8806
            }
          },
          {
            "name": "False northing",
            "value": 0,
            "unit": "metre",
            "id": {
              "authority": "EPSG",
              "code": 8807
            }
          }
        ]
      },
      "coordinate_system": {
        "subtype": "Cartesian",
        "axis": [
          {
            "name": "Easting",
            "abbreviation": "",
            "direction": "east",
            "unit": "metre"
          },
          {
            "name": "Northing",
            "abbreviation": "",
            "direction": "north",
            "unit": "metre"
          }
        ]
      },
      "id": {
        "authority": "EPSG",
        "code": 26913
      }
    },
    "datetime": null,
    "proj:code": "EPSG:26913"
  },
  "links": [
    {
      "rel": "root",
      "href": "./collection.json",
      "type": "application/json"
    },
    {
      "rel": "collection",
      "href": "./collection.json",
      "type": "application/json"
    },
    {
      "rel": "parent",
      "href": "./collection.json",
      "type": "application/json"
    }
  ],
  "assets": {
    "elevation": {
      "href": "https://prd-tnm.s3.amazonaws.com/StagedProducts/Elevation/1m/Projects/ND_SouthWest_2021_D21/TIFF/USGS_1M_13_x58y524_ND_SouthWest_2021_D21.tif",
      "type": "image/tiff; application=geotiff",
      "raster:bands": [
        {
          "data_type": "float32",
          "scale": 1.0,
          "offset": 0.0,
          "sampling": "area",
          "nodata": -999999.0,
          "statistics": {
            "mean": 759.7858276367188,
            "minimum": 678.4512329101562,
            "maximum": 831.0745849609375,
            "stddev": 29.195171824914947,
            "valid_percent": 100.0
          },
          "histogram": {
            "count": 11,
            "min": 678.4512329101562,
            "max": 831.0745849609375,
            "buckets": [
              33756,
              29223,
              60075,
              120551,
              190579,
              195257,
              195585,
              159252,
              57626,
              6672
            ]
          }
        }
      ],
      "roles": [
        "data"
      ]
    }
  },
  "collection": "ND_SouthWest_2021_D21"
}