{
  "type": "Feature",
  "stac_version": "1.1.0",
  "stac_extensions": [
    "https://stac-extensions.github.io/projection/v2.0.0/schema.json",
    "https://stac-extensions.github.io/raster/v1.1.0/schema.json"
  ],
  "id": "USGS_1M_17_x46y427_WV_FEMAHQ_2018_D18",
  "geometry": {
    "type": "Polygon",
    "coordinates": [
      [
        [
          -81.45871452130824,
          38.487391174977695
        ],
        [
          -81.3439177324804,
          38.48778449048655
        ],
        [
          -81.34434754217716,
          38.578011798494224
        ],
        [
          -81.45928778704774,
          38.5776172180591
        ],
        [
          -81.45871452130824,
          38.487391174977695
        ]
      ]
    ]
  },
  "bbox": [
    -81.45928778704774,
    38.487391174977695,
    -81.3439177324804,
    38.578011798494224
  ],
  "properties": {
    "start_datetime": "2018-11-08T00:00:00Z",
    "end_datetime": "2019-05-01T00:00:00Z",
    "proj:geometry": {
      "type": "Polygon",
      "coordinates": [
        [
          [
            459994.0000117545,
            4259994.000044274
          ],
          [
            470006.0000117545,
            4259994.000044274
          ],
          [
            470006.0000117545,
            4270006.000044274
          ],
          [
            459994.0000117545,
            4270006.000044274
          ],
          [
            459994.0000117545,
            4259994.000044274
          ]
        ]
      ]
    },
    "proj:bbox": [
      459994.0000117545,
      4259994.000044274,
      470006.0000117545,
      4270006.000044274
    ],
    "proj:shape": [
      10012,
      10012
    ],
    "proj:transform": [
      1.0,
      0.0,
      459994.0000117545,
      0.0,
      -1.0,
      4270006.000044274,
      0.0,
      0.0,
      1.0
    ],
    "proj:projjson": {
      "$schema": "https://proj.org/schemas/v0.7/projjson.schema.json",
      "type": "ProjectedCRS",
      "name": "NAD83 / UTM zone 17N",
      "base_crs": {
        "name": "NAD83",
        "datum": {
          "type": "GeodeticReferenceFrame",
          "name": "North American Datum 1983",
          "ellipsoid": {
            "name": "GRS 1980",
            "semi_major_axis": 6378137,
            "inverse_flattening": 298.257222101
          }
        },
        "coordinate_system": {
          "subtype": "ellipsoidal",
          "axis": [
            {
              "name": "Geodetic latitude",
              "abbreviation": "Lat",
              "direction": "north",
              "unit": "degree"
            },
            {
              "name": "Geodetic longitude",
              "abbreviation": "Lon",
              "direction": "east",
              "unit": "degree"
            }
          ]
        },
        "id": {
          "authority": "EPSG",
          "code": 4269
        }
      },
      "conversion": {
        "name": "UTM zone 17N",
        "method": {
          "name": "Transverse Mercator",
          "id": {
            "authority": "EPSG",
            "code": 9807
          }
        },
        "parameters": [
          {
            "name": "Latitude of natural origin",
            "value": 0,
            "unit": "degree",
            "id": {
              "authority": "EPSG",
              "code": 8801
            }
          },
          {
            "name": "Longitude of natural origin",
            "value": -81,
            "unit": "degree",
            "id": {
              "authority": "EPSG",
              "code": 8802
            }
          },
          {
            "name": "Scale factor at natural origin",
            "value": 0.9996,
            "unit": "unity",
            "id": {
              "authority": "EPSG",
              "code": 8805
            }
          },
          {
            "name": "False easting",
            "value": 500000,
            "unit": "metre",
            "id": {
              "authority": "EPSG",
              "code": 8806
            }
          },
          {
            "name": "False northing",
            "value": 0,
            "unit": "metre",
            "id": {
              "authority": "EPSG",
              "code": 8807
            }
          }
        ]
      },
      "coordinate_system": {
        "subtype": "Cartesian",
        "axis": [
          {
            "name": "Easting",
            "abbreviation": "",
            "direction": "east",
            "unit": "metre"
          },
          {
            "name": "Northing",
            "abbreviation": "",
            "direction": "north",
            "unit": "metre"
          }
        ]
      },
      "id": {
        "authority": "EPSG",
        "code": 26917
      }
    },
    "datetime": null,
    "proj:code": "EPSG:26917"
  },
  "links": [
    {
      "rel": "root",
      "href": "./collection.json",
      "type": "application/json"
    },
    {
      "rel": "collection",
      "href": "./collection.json",
      "type": "application/json"
    },
    {
      "rel": "parent",
      "href": "./collection.json",
      "type": "application/json"
    }
  ],
  "assets": {
    "elevation": {
      "href": "https://prd-tnm.s3.amazonaws.com/StagedProducts/Elevation/1m/Projects/WV_FEMAHQ_2018_D18/TIFF/USGS_1M_17_x46y427_WV_FEMAHQ_2018_D18.tif",
      "type": "image/tiff; application=geotiff",
      "raster:bands": [
        {
          "data_type": "float32",
          "scale": 1.0,
          "offset": 0.0,
          "sampling": "area",
          "nodata": -999999.0,
          "statistics": {
            "mean": 296.065542555573,
            "minimum": 192.6676788330078,
            "maximum": 399.4767150878906,
            "stddev": 36.70662314719284,
            "valid_percent": 37.062931060791016
          },
          "histogram": {
            "count": 11,
            "min": 192.6676788330078,
            "max": 399.4767150878906,
            "buckets": [
              7591,
              15215,
              34749,
              53351,
              67933,
              88120,
              72392,
              38629,
              9700,
              953
            ]
          }
        }
      ],
      "roles": [
        "data"
      ]
    }
  },
  "collection": "WV_FEMAHQ_2018_D18"
}