{
  "type": "Feature",
  "stac_version": "1.1.0",
  "stac_extensions": [
    "https://stac-extensions.github.io/projection/v2.0.0/schema.json",
    "https://stac-extensions.github.io/raster/v1.1.0/schema.json"
  ],
  "id": "USGS_1M_15_x63y417_MO_7County_D23",
  "geometry": {
    "type": "Polygon",
    "coordinates": [
      [
        [
          -91.52782712379859,
          37.57782411895402
        ],
        [
          -91.41448029084235,
          37.57635582020114
        ],
        [
          -91.41256284439407,
          37.66656410620822
        ],
        [
          -91.52604662765145,
          37.66803716392827
        ],
        [
          -91.52782712379859,
          37.57782411895402
        ]
      ]
    ]
  },
  "bbox": [
    -91.52782712379859,
    37.57635582020114,
    -91.41256284439407,
    37.66803716392827
  ],
  "properties": {
    "start_datetime": "2023-04-05T00:00:00Z",
    "end_datetime": "2023-04-19T00:00:00Z",
    "proj:geometry": {
      "type": "Polygon",
      "coordinates": [
        [
          [
            629994.0000004811,
            4159994.000322823
          ],
          [
            640006.0000004811,
            4159994.000322823
          ],
          [
            640006.0000004811,
            4170006.000322823
          ],
          [
            629994.0000004811,
            4170006.000322823
          ],
          [
            629994.0000004811,
            4159994.000322823
          ]
        ]
      ]
    },
    "proj:bbox": [
      629994.0000004811,
      4159994.000322823,
      640006.0000004811,
      4170006.000322823
    ],
    "proj:shape": [
      10012,
      10012
    ],
    "proj:transform": [
      1.0,
      0.0,
      629994.0000004811,
      0.0,
      -1.0,
      4170006.000322823,
      0.0,
      0.0,
      1.0
    ],
    "proj:projjson": {
      "$schema": "https://proj.org/schemas/v0.7/projjson.schema.json",
      "type": "ProjectedCRS",
      "name": "NAD83 / UTM zone 15N",
      "base_crs": {
        "name": "NAD83",
        "datum": {
          "type": "GeodeticReferenceFrame",
          "name": "North American Datum 1983",
          "ellipsoid": {
            "name": "GRS 1980",
            "semi_major_axis": 6378137,
            "inverse_flattening": 298.257222101
          }
        },
        "coordinate_system": {
          "subtype": "ellipsoidal",
          "axis": [
            {
              "name": "Geodetic latitude",
              "abbreviation": "Lat",
              "direction": "north",
              "unit": "degree"
            },
            {
              "name": "Geodetic longitude",
              "abbreviation": "Lon",
              "direction": "east",
              "unit": "degree"
            }
          ]
        },
        "id": {
          "authority": "EPSG",
          "code": 4269
        }
      },
      "conversion": {
        "name": "UTM zone 15N",
        "method": {
          "name": "Transverse Mercator",
          "id": {
            "authority": "EPSG",
            "code": 9807
          }
        },
        "parameters": [
          {
            "name": "Latitude of natural origin",
            "value": 0,
            "unit": "degree",
            "id": {
              "authority": "EPSG",
              "code": 8801
            }
          },
          {
            "name": "Longitude of natural origin",
            "value": -93,
            "unit": "degree",
            "id": {
              "authority": "EPSG",
              "code": 8802
            }
          },
          {
            "name": "Scale factor at natural origin",
            "value": 0.9996,
            "unit": "unity",
            "id": {
              "authority": "EPSG",
              "code": 8805
            }
          },
          {
            "name": "False easting",
            "value": 500000,
            "unit": "metre",
            "id": {
              "authority": "EPSG",
              "code": 8806
            }
          },
          {
            "name": "False northing",
            "value": 0,
            "unit": "metre",
            "id": {
              "authority": "EPSG",
              "code": 8807
            }
          }
        ]
      },
      "coordinate_system": {
        "subtype": "Cartesian",
        "axis": [
          {
            "name": "Easting",
            "abbreviation": "",
            "direction": "east",
            "unit": "metre"
          },
          {
            "name": "Northing",
            "abbreviation": "",
            "direction": "north",
            "unit": "metre"
          }
        ]
      },
      "id": {
        "authority": "EPSG",
        "code": 26915
      }
    },
    "datetime": null,
    "proj:code": "EPSG:26915"
  },
  "links": [
    {
      "rel": "root",
      "href": "./collection.json",
      "type": "application/json"
    },
    {
      "rel": "collection",
      "href": "./collection.json",
      "type": "application/json"
    },
    {
      "rel": "parent",
      "href": "./collection.json",
      "type": "application/json"
    }
  ],
  "assets": {
    "elevation": {
      "href": "https://prd-tnm.s3.amazonaws.com/StagedProducts/Elevation/1m/Projects/MO_7County_D23/TIFF/USGS_1M_15_x63y417_MO_7County_D23.tif",
      "type": "image/tiff; application=geotiff",
      "raster:bands": [
        {
          "data_type": "float32",
          "scale": 1.0,
          "offset": 0.0,
          "sampling": "area",
          "nodata": -999999.0,
          "statistics": {
            "mean": 364.729922598897,
            "minimum": 312.242431640625,
            "maximum": 398.8940124511719,
            "stddev": 16.052908167052543,
            "valid_percent": 12.000846862792969
          },
          "histogram": {
            "count": 11,
            "min": 312.242431640625,
            "max": 398.8940124511719,
            "buckets": [
              586,
              2882,
              5576,
              9336,
              15598,
              21184,
              28858,
              22267,
              16267,
              3284
            ]
          }
        }
      ],
      "roles": [
        "data"
      ]
    }
  },
  "collection": "MO_7County_D23"
}