{
  "type": "Feature",
  "stac_version": "1.1.0",
  "stac_extensions": [
    "https://stac-extensions.github.io/projection/v2.0.0/schema.json",
    "https://stac-extensions.github.io/raster/v1.1.0/schema.json"
  ],
  "id": "USGS_1M_16_x33y472_WI_8County_2020_A20",
  "geometry": {
    "type": "Polygon",
    "coordinates": [
      [
        [
          -89.06979220039248,
          42.523640142783854
        ],
        [
          -88.94796857334899,
          42.52577650999614
        ],
        [
          -88.95077579225845,
          42.61588997521866
        ],
        [
          -89.07277468221358,
          42.61374689839169
        ],
        [
          -89.06979220039248,
          42.523640142783854
        ]
      ]
    ]
  },
  "bbox": [
    -89.07277468221358,
    42.523640142783854,
    -88.94796857334899,
    42.61588997521866
  ],
  "properties": {
    "start_datetime": "2020-04-11T00:00:00Z",
    "end_datetime": "2020-04-21T00:00:00Z",
    "proj:geometry": {
      "type": "Polygon",
      "coordinates": [
        [
          [
            329993.9996633329,
            4709994.000336507
          ],
          [
            340005.9996633329,
            4709994.000336507
          ],
          [
            340005.9996633329,
            4720006.000336507
          ],
          [
            329993.9996633329,
            4720006.000336507
          ],
          [
            329993.9996633329,
            4709994.000336507
          ]
        ]
      ]
    },
    "proj:bbox": [
      329993.9996633329,
      4709994.000336507,
      340005.9996633329,
      4720006.000336507
    ],
    "proj:shape": [
      10012,
      10012
    ],
    "proj:transform": [
      1.0,
      0.0,
      329993.9996633329,
      0.0,
      -1.0,
      4720006.000336507,
      0.0,
      0.0,
      1.0
    ],
    "proj:projjson": {
      "$schema": "https://proj.org/schemas/v0.7/projjson.schema.json",
      "type": "ProjectedCRS",
      "name": "NAD83 / UTM zone 16N",
      "base_crs": {
        "name": "NAD83",
        "datum": {
          "type": "GeodeticReferenceFrame",
          "name": "North American Datum 1983",
          "ellipsoid": {
            "name": "GRS 1980",
            "semi_major_axis": 6378137,
            "inverse_flattening": 298.257222101
          }
        },
        "coordinate_system": {
          "subtype": "ellipsoidal",
          "axis": [
            {
              "name": "Geodetic latitude",
              "abbreviation": "Lat",
              "direction": "north",
              "unit": "degree"
            },
            {
              "name": "Geodetic longitude",
              "abbreviation": "Lon",
              "direction": "east",
              "unit": "degree"
            }
          ]
        },
        "id": {
          "authority": "EPSG",
          "code": 4269
        }
      },
      "conversion": {
        "name": "UTM zone 16N",
        "method": {
          "name": "Transverse Mercator",
          "id": {
            "authority": "EPSG",
            "code": 9807
          }
        },
        "parameters": [
          {
            "name": "Latitude of natural origin",
            "value": 0,
            "unit": "degree",
            "id": {
              "authority": "EPSG",
              "code": 8801
            }
          },
          {
            "name": "Longitude of natural origin",
            "value": -87,
            "unit": "degree",
            "id": {
              "authority": "EPSG",
              "code": 8802
            }
          },
          {
            "name": "Scale factor at natural origin",
            "value": 0.9996,
            "unit": "unity",
            "id": {
              "authority": "EPSG",
              "code": 8805
            }
          },
          {
            "name": "False easting",
            "value": 500000,
            "unit": "metre",
            "id": {
              "authority": "EPSG",
              "code": 8806
            }
          },
          {
            "name": "False northing",
            "value": 0,
            "unit": "metre",
            "id": {
              "authority": "EPSG",
              "code": 8807
            }
          }
        ]
      },
      "coordinate_system": {
        "subtype": "Cartesian",
        "axis": [
          {
            "name": "Easting",
            "abbreviation": "",
            "direction": "east",
            "unit": "metre"
          },
          {
            "name": "Northing",
            "abbreviation": "",
            "direction": "north",
            "unit": "metre"
          }
        ]
      },
      "id": {
        "authority": "EPSG",
        "code": 26916
      }
    },
    "datetime": null,
    "proj:code": "EPSG:26916"
  },
  "links": [
    {
      "rel": "root",
      "href": "./collection.json",
      "type": "application/json"
    },
    {
      "rel": "collection",
      "href": "./collection.json",
      "type": "application/json"
    },
    {
      "rel": "parent",
      "href": "./collection.json",
      "type": "application/json"
    }
  ],
  "assets": {
    "elevation": {
      "href": "https://prd-tnm.s3.amazonaws.com/StagedProducts/Elevation/1m/Projects/WI_8County_2020_A20/TIFF/USGS_1M_16_x33y472_WI_8County_2020_A20.tif",
      "type": "image/tiff; application=geotiff",
      "raster:bands": [
        {
          "data_type": "float32",
          "scale": 1.0,
          "offset": 0.0,
          "sampling": "area",
          "nodata": -999999.0,
          "statistics": {
            "mean": 246.04177856445312,
            "minimum": 226.7624969482422,
            "maximum": 287.4985046386719,
            "stddev": 9.931849040257232,
            "valid_percent": 100.0
          },
          "histogram": {
            "count": 11,
            "min": 226.7624969482422,
            "max": 287.4985046386719,
            "buckets": [
              125843,
              93315,
              260695,
              277252,
              178495,
              57493,
              34859,
              16254,
              3393,
              977
            ]
          }
        }
      ],
      "roles": [
        "data"
      ]
    }
  },
  "collection": "WI_8County_2020_A20"
}