{
  "type": "Feature",
  "stac_version": "1.1.0",
  "stac_extensions": [
    "https://stac-extensions.github.io/projection/v2.0.0/schema.json",
    "https://stac-extensions.github.io/raster/v1.1.0/schema.json"
  ],
  "id": "USGS_1M_12_x32y379_AZ_Yavapai_2021_B21",
  "geometry": {
    "type": "Polygon",
    "coordinates": [
      [
        [
          -112.95240835546498,
          34.14534872593496
        ],
        [
          -112.8438655567556,
          34.14702749641421
        ],
        [
          -112.84583141677672,
          34.23727514709969
        ],
        [
          -112.95448976522368,
          34.235590711604246
        ],
        [
          -112.95240835546498,
          34.14534872593496
        ]
      ]
    ]
  },
  "bbox": [
    -112.95448976522368,
    34.14534872593496,
    -112.8438655567556,
    34.23727514709969
  ],
  "properties": {
    "start_datetime": "2021-09-13T00:00:00Z",
    "end_datetime": "2021-11-13T00:00:00Z",
    "proj:geometry": {
      "type": "Polygon",
      "coordinates": [
        [
          [
            319994.00000152475,
            3779994.0000371775
          ],
          [
            330006.00000152475,
            3779994.0000371775
          ],
          [
            330006.00000152475,
            3790006.0000371775
          ],
          [
            319994.00000152475,
            3790006.0000371775
          ],
          [
            319994.00000152475,
            3779994.0000371775
          ]
        ]
      ]
    },
    "proj:bbox": [
      319994.00000152475,
      3779994.0000371775,
      330006.00000152475,
      3790006.0000371775
    ],
    "proj:shape": [
      10012,
      10012
    ],
    "proj:transform": [
      1.0,
      0.0,
      319994.00000152475,
      0.0,
      -1.0,
      3790006.0000371775,
      0.0,
      0.0,
      1.0
    ],
    "proj:projjson": {
      "$schema": "https://proj.org/schemas/v0.7/projjson.schema.json",
      "type": "ProjectedCRS",
      "name": "NAD83 / UTM zone 12N",
      "base_crs": {
        "name": "NAD83",
        "datum": {
          "type": "GeodeticReferenceFrame",
          "name": "North American Datum 1983",
          "ellipsoid": {
            "name": "GRS 1980",
            "semi_major_axis": 6378137,
            "inverse_flattening": 298.257222101
          }
        },
        "coordinate_system": {
          "subtype": "ellipsoidal",
          "axis": [
            {
              "name": "Geodetic latitude",
              "abbreviation": "Lat",
              "direction": "north",
              "unit": "degree"
            },
            {
              "name": "Geodetic longitude",
              "abbreviation": "Lon",
              "direction": "east",
              "unit": "degree"
            }
          ]
        },
        "id": {
          "authority": "EPSG",
          "code": 4269
        }
      },
      "conversion": {
        "name": "UTM zone 12N",
        "method": {
          "name": "Transverse Mercator",
          "id": {
            "authority": "EPSG",
            "code": 9807
          }
        },
        "parameters": [
          {
            "name": "Latitude of natural origin",
            "value": 0,
            "unit": "degree",
            "id": {
              "authority": "EPSG",
              "code": 8801
            }
          },
          {
            "name": "Longitude of natural origin",
            "value": -111,
            "unit": "degree",
            "id": {
              "authority": "EPSG",
              "code": 8802
            }
          },
          {
            "name": "Scale factor at natural origin",
            "value": 0.9996,
            "unit": "unity",
            "id": {
              "authority": "EPSG",
              "code": 8805
            }
          },
          {
            "name": "False easting",
            "value": 500000,
            "unit": "metre",
            "id": {
              "authority": "EPSG",
              "code": 8806
            }
          },
          {
            "name": "False northing",
            "value": 0,
            "unit": "metre",
            "id": {
              "authority": "EPSG",
              "code": 8807
            }
          }
        ]
      },
      "coordinate_system": {
        "subtype": "Cartesian",
        "axis": [
          {
            "name": "Easting",
            "abbreviation": "",
            "direction": "east",
            "unit": "metre"
          },
          {
            "name": "Northing",
            "abbreviation": "",
            "direction": "north",
            "unit": "metre"
          }
        ]
      },
      "id": {
        "authority": "EPSG",
        "code": 26912
      }
    },
    "datetime": null,
    "proj:code": "EPSG:26912"
  },
  "links": [
    {
      "rel": "root",
      "href": "./collection.json",
      "type": "application/json"
    },
    {
      "rel": "collection",
      "href": "./collection.json",
      "type": "application/json"
    },
    {
      "rel": "parent",
      "href": "./collection.json",
      "type": "application/json"
    }
  ],
  "assets": {
    "elevation": {
      "href": "https://prd-tnm.s3.amazonaws.com/StagedProducts/Elevation/1m/Projects/AZ_Yavapai_2021_B21/TIFF/USGS_1M_12_x32y379_AZ_Yavapai_2021_B21.tif",
      "type": "image/tiff; application=geotiff",
      "raster:bands": [
        {
          "data_type": "float32",
          "scale": 1.0,
          "offset": 0.0,
          "sampling": "area",
          "nodata": -999999.0,
          "statistics": {
            "mean": 1029.7376708984375,
            "minimum": 877.9937133789062,
            "maximum": 1503.1016845703125,
            "stddev": 117.82698262964523,
            "valid_percent": 100.0
          },
          "histogram": {
            "count": 11,
            "min": 877.9937133789062,
            "max": 1503.1016845703125,
            "buckets": [
              299341,
              245591,
              171704,
              100985,
              117350,
              58675,
              29650,
              15438,
              6757,
              3085
            ]
          }
        }
      ],
      "roles": [
        "data"
      ]
    }
  },
  "collection": "AZ_Yavapai_2021_B21"
}