{
  "type": "Feature",
  "stac_version": "1.1.0",
  "stac_extensions": [
    "https://stac-extensions.github.io/projection/v2.0.0/schema.json",
    "https://stac-extensions.github.io/raster/v1.1.0/schema.json"
  ],
  "id": "USGS_1M_16_x43y489_WI_2County_B23",
  "geometry": {
    "type": "Polygon",
    "coordinates": [
      [
        [
          -87.87419862022398,
          44.0697739442696
        ],
        [
          -87.74918542575654,
          44.07066212928789
        ],
        [
          -87.7503251375822,
          44.16079570474023
        ],
        [
          -87.87552845568769,
          44.159904738387
        ],
        [
          -87.87419862022398,
          44.0697739442696
        ]
      ]
    ]
  },
  "bbox": [
    -87.87552845568769,
    44.0697739442696,
    -87.74918542575654,
    44.16079570474023
  ],
  "properties": {
    "start_datetime": "2023-04-18T00:00:00Z",
    "end_datetime": "2023-05-21T00:00:00Z",
    "proj:geometry": {
      "type": "Polygon",
      "coordinates": [
        [
          [
            429993.9996759052,
            4879994.000307111
          ],
          [
            440005.9996759052,
            4879994.000307111
          ],
          [
            440005.9996759052,
            4890006.000307111
          ],
          [
            429993.9996759052,
            4890006.000307111
          ],
          [
            429993.9996759052,
            4879994.000307111
          ]
        ]
      ]
    },
    "proj:bbox": [
      429993.9996759052,
      4879994.000307111,
      440005.9996759052,
      4890006.000307111
    ],
    "proj:shape": [
      10012,
      10012
    ],
    "proj:transform": [
      1.0,
      0.0,
      429993.9996759052,
      0.0,
      -1.0,
      4890006.000307111,
      0.0,
      0.0,
      1.0
    ],
    "proj:projjson": {
      "$schema": "https://proj.org/schemas/v0.7/projjson.schema.json",
      "type": "ProjectedCRS",
      "name": "NAD83 / UTM zone 16N",
      "base_crs": {
        "name": "NAD83",
        "datum": {
          "type": "GeodeticReferenceFrame",
          "name": "North American Datum 1983",
          "ellipsoid": {
            "name": "GRS 1980",
            "semi_major_axis": 6378137,
            "inverse_flattening": 298.257222101
          }
        },
        "coordinate_system": {
          "subtype": "ellipsoidal",
          "axis": [
            {
              "name": "Geodetic latitude",
              "abbreviation": "Lat",
              "direction": "north",
              "unit": "degree"
            },
            {
              "name": "Geodetic longitude",
              "abbreviation": "Lon",
              "direction": "east",
              "unit": "degree"
            }
          ]
        },
        "id": {
          "authority": "EPSG",
          "code": 4269
        }
      },
      "conversion": {
        "name": "UTM zone 16N",
        "method": {
          "name": "Transverse Mercator",
          "id": {
            "authority": "EPSG",
            "code": 9807
          }
        },
        "parameters": [
          {
            "name": "Latitude of natural origin",
            "value": 0,
            "unit": "degree",
            "id": {
              "authority": "EPSG",
              "code": 8801
            }
          },
          {
            "name": "Longitude of natural origin",
            "value": -87,
            "unit": "degree",
            "id": {
              "authority": "EPSG",
              "code": 8802
            }
          },
          {
            "name": "Scale factor at natural origin",
            "value": 0.9996,
            "unit": "unity",
            "id": {
              "authority": "EPSG",
              "code": 8805
            }
          },
          {
            "name": "False easting",
            "value": 500000,
            "unit": "metre",
            "id": {
              "authority": "EPSG",
              "code": 8806
            }
          },
          {
            "name": "False northing",
            "value": 0,
            "unit": "metre",
            "id": {
              "authority": "EPSG",
              "code": 8807
            }
          }
        ]
      },
      "coordinate_system": {
        "subtype": "Cartesian",
        "axis": [
          {
            "name": "Easting",
            "abbreviation": "",
            "direction": "east",
            "unit": "metre"
          },
          {
            "name": "Northing",
            "abbreviation": "",
            "direction": "north",
            "unit": "metre"
          }
        ]
      },
      "id": {
        "authority": "EPSG",
        "code": 26916
      }
    },
    "datetime": null,
    "proj:code": "EPSG:26916"
  },
  "links": [
    {
      "rel": "root",
      "href": "./collection.json",
      "type": "application/json"
    },
    {
      "rel": "collection",
      "href": "./collection.json",
      "type": "application/json"
    },
    {
      "rel": "parent",
      "href": "./collection.json",
      "type": "application/json"
    }
  ],
  "assets": {
    "elevation": {
      "href": "https://prd-tnm.s3.amazonaws.com/StagedProducts/Elevation/1m/Projects/WI_2County_B23/TIFF/USGS_1M_16_x43y489_WI_2County_B23.tif",
      "type": "image/tiff; application=geotiff",
      "raster:bands": [
        {
          "data_type": "float32",
          "scale": 1.0,
          "offset": 0.0,
          "sampling": "area",
          "nodata": -999999.0,
          "statistics": {
            "mean": 244.36695861816406,
            "minimum": 202.02272033691406,
            "maximum": 288.4892578125,
            "stddev": 16.234967241302247,
            "valid_percent": 100.0
          },
          "histogram": {
            "count": 11,
            "min": 202.02272033691406,
            "max": 288.4892578125,
            "buckets": [
              11482,
              39979,
              132845,
              190332,
              185672,
              154690,
              186941,
              92732,
              44132,
              9771
            ]
          }
        }
      ],
      "roles": [
        "data"
      ]
    }
  },
  "collection": "WI_2County_B23"
}